[
  {
    "base": "linux-odroid-511",
    "name": "linux-odroid-511-headers",
    "arch": "aarch64",
    "description": "Header files and scripts for building modules for linux kernel - Tobetter Odroid Branch",
    "url": "https://github.com/tobetter/linux/tree/odroid-5.11.y",
    "license": "GPL2",
    "version": "5.11.13",
    "release": "1",
    "builddate": "2021-04-14T19:58:15",
    "conflicts": [
      "linux-headers"
    ],
    "csize": 12567905,
    "isize": 48384904
  },
  {
    "base": "linux-odroid-511",
    "name": "linux-odroid-511",
    "arch": "aarch64",
    "description": "The Linux Kernel and modules - Tobetter Odroid Branch",
    "url": "https://github.com/tobetter/linux/tree/odroid-5.11.y",
    "license": "GPL2",
    "version": "5.11.13",
    "release": "1",
    "builddate": "2021-04-14T19:58:15",
    "depends": [
      "coreutils",
      "linux-firmware",
      "kmod",
      "mkinitcpio>=0.7"
    ],
    "optdepends": [
      "crda: to set the correct wireless channels of your country"
    ],
    "replaces": [
      "linux-armv8"
    ],
    "conflicts": [
      "linux"
    ],
    "csize": 57924218,
    "isize": 161941679
  },
  {
    "base": "linux-amlogic-exp",
    "name": "linux-amlogic-exp-headers",
    "arch": "aarch64",
    "description": "Header files and scripts for building modules for linux kernel - Chewitt Amlogic Branch (Experimental)",
    "url": "https://github.com/chewitt/linux/tree/amlogic-5.12.y",
    "license": "GPL2",
    "version": "5.12",
    "release": "7",
    "builddate": "2021-04-14T19:42:22",
    "conflicts": [
      "linux-headers"
    ],
    "csize": 12742153,
    "isize": 48963319
  },
  {
    "base": "linux-amlogic-exp",
    "name": "linux-amlogic-exp",
    "arch": "aarch64",
    "description": "The Linux Kernel and modules - Chewitt Amlogic Branch (Experimental)",
    "url": "https://github.com/chewitt/linux/tree/amlogic-5.12.y",
    "license": "GPL2",
    "version": "5.12",
    "release": "7",
    "builddate": "2021-04-14T19:42:22",
    "depends": [
      "coreutils",
      "linux-firmware",
      "kmod",
      "mkinitcpio>=0.7"
    ],
    "optdepends": [
      "crda: to set the correct wireless channels of your country"
    ],
    "replaces": [
      "linux-armv8"
    ],
    "conflicts": [
      "linux"
    ],
    "csize": 58270387,
    "isize": 163443947
  },
  {
    "base": "mesa-devel-git",
    "name": "mesa-devel-git",
    "arch": "aarch64",
    "description": "Open-source implementation of the OpenGL specification (development version)",
    "url": "https://www.mesa3d.org/",
    "license": "custom",
    "version": "21.1.0_devel.138048.d6db4d2e081",
    "release": "1",
    "builddate": "2021-04-14T07:50:13",
    "depends": [
      "libdrm",
      "libxxf86vm",
      "libxdamage",
      "libxshmfence",
      "libelf",
      "libomxil-bellagio",
      "libunwind",
      "libglvnd",
      "llvm",
      "lm_sensors",
      "libclc",
      "glslang",
      "vulkan-icd-loader",
      "wayland",
      "zstd"
    ],
    "replaces": [
      "mesa-dri",
      "mesa-libgl",
      "mesa-arm-git"
    ],
    "conflicts": [
      "vulkan-mesa-layers",
      "opencl-mesa",
      "vulkan-swrast",
      "libva-mesa-driver",
      "mesa-vdpau",
      "mesa",
      "mesa-dri",
      "mesa-libgl"
    ],
    "csize": 28970936,
    "isize": 98457064
  },
  {
    "base": "mesa-icecream95-git",
    "name": "mesa-icecream95-git",
    "arch": "aarch64",
    "description": "Open-source implementation of the OpenGL specification (latest icrecream95 branch)",
    "url": "https://www.mesa3d.org/",
    "license": "custom",
    "version": "21.1.0_devel.137849.c1e10cef065",
    "release": "1",
    "builddate": "2021-04-13T22:01:43",
    "depends": [
      "libdrm",
      "libxxf86vm",
      "libxdamage",
      "libxshmfence",
      "libelf",
      "libomxil-bellagio",
      "libunwind",
      "libglvnd",
      "llvm",
      "lm_sensors",
      "libclc",
      "glslang",
      "vulkan-icd-loader",
      "wayland",
      "zstd"
    ],
    "replaces": [
      "mesa-dri",
      "mesa-libgl"
    ],
    "conflicts": [
      "vulkan-mesa-layers",
      "opencl-mesa",
      "vulkan-swrast",
      "libva-mesa-driver",
      "mesa-vdpau",
      "mesa",
      "mesa-dri",
      "mesa-libgl"
    ],
    "csize": 28940148,
    "isize": 98456514
  },
  {
    "base": "mesa-devel",
    "name": "mesa-devel",
    "arch": "aarch64",
    "description": "Open-source implementation of the OpenGL specification (Development version pinned to a stable and tested commit)",
    "url": "https://www.mesa3d.org/",
    "license": "custom",
    "version": "21.1.0_devel.137845.0dfc5b51967",
    "release": "1",
    "builddate": "2021-04-12T21:53:49",
    "depends": [
      "libdrm",
      "libxxf86vm",
      "libxdamage",
      "libxshmfence",
      "libelf",
      "libomxil-bellagio",
      "libunwind",
      "libglvnd",
      "llvm",
      "lm_sensors",
      "libclc",
      "glslang",
      "vulkan-icd-loader",
      "wayland",
      "zstd"
    ],
    "replaces": [
      "mesa-dri",
      "mesa-libgl",
      "mesa-arm"
    ],
    "conflicts": [
      "vulkan-mesa-layers",
      "opencl-mesa",
      "vulkan-swrast",
      "libva-mesa-driver",
      "mesa-vdpau",
      "mesa",
      "mesa-dri",
      "mesa-libgl"
    ],
    "csize": 28736623,
    "isize": 94954562
  },
  {
    "base": "linux-amlogic-512",
    "name": "linux-amlogic-512-headers",
    "arch": "aarch64",
    "description": "Header files and scripts for building modules for linux kernel - Chewitt Amlogic Branch",
    "url": "https://github.com/chewitt/linux/tree/amlogic-5.12.y",
    "license": "GPL2",
    "version": "5.12",
    "release": "7",
    "builddate": "2021-04-12T18:03:54",
    "conflicts": [
      "linux-headers"
    ],
    "csize": 12742241,
    "isize": 48963319
  },
  {
    "base": "linux-amlogic-512",
    "name": "linux-amlogic-512",
    "arch": "aarch64",
    "description": "The Linux Kernel and modules - Chewitt Amlogic Branch",
    "url": "https://github.com/chewitt/linux/tree/amlogic-5.12.y",
    "license": "GPL2",
    "version": "5.12",
    "release": "7",
    "builddate": "2021-04-12T18:03:54",
    "depends": [
      "coreutils",
      "linux-firmware",
      "kmod",
      "mkinitcpio>=0.7"
    ],
    "optdepends": [
      "crda: to set the correct wireless channels of your country"
    ],
    "replaces": [
      "linux-armv8"
    ],
    "conflicts": [
      "linux"
    ],
    "csize": 58269437,
    "isize": 163444264
  },
  {
    "base": "uboot-odroid-n2plus",
    "name": "uboot-odroid-n2plus",
    "arch": "aarch64",
    "description": "U-Boot for ODROID-N2/N2+",
    "url": "https://github.com/hardkernel/u-boot",
    "license": "GPL",
    "version": "2015.01.189",
    "release": "1",
    "builddate": "2021-04-09T22:33:08",
    "depends": [
      "uboot-tools",
      "util-linux",
      "gawk",
      "sed"
    ],
    "conflicts": [
      "uboot-odroid-n2"
    ],
    "csize": 581857,
    "isize": 876022
  }
]
